{
  "date": "2026-06-24",
  "markets": {
    "us": {
      "full_ic_20d": -0.1556,
      "recent_ic_20d": 0.3439,
      "ic_trend": "decaying",
      "ic_change_pct": 121.0,
      "score_mean_60d": 82.1,
      "score_std_60d": 10.7,
      "zone_distribution_60d": {
        "extreme_fear": 0,
        "fear": 0,
        "neutral": 4,
        "greed": 10,
        "extreme_greed": 41
      },
      "health": "good",
      "flags": [
        "IC decaying: recent 0.3439 vs historical -0.1556",
        "Calibration stale: 2026-03-25 (91d ago)"
      ],
      "calibration_stale": true,
      "calibration_days_ago": 91
    },
    "tw": {
      "full_ic_20d": -0.1145,
      "recent_ic_20d": 0.3403,
      "ic_trend": "decaying",
      "ic_change_pct": 197.2,
      "score_mean_60d": 91.8,
      "score_std_60d": 7.3,
      "zone_distribution_60d": {
        "extreme_fear": 0,
        "fear": 0,
        "neutral": 0,
        "greed": 2,
        "extreme_greed": 30
      },
      "health": "good",
      "flags": [
        "IC decaying: recent 0.3403 vs historical -0.1145",
        "Score stuck in extreme_greed zone 94% of last 60d",
        "Calibration stale: 2026-04-11 (74d ago)"
      ],
      "calibration_stale": true,
      "calibration_days_ago": 74
    },
    "jp": {
      "full_ic_20d": -0.0678,
      "recent_ic_20d": -0.0033,
      "ic_trend": "decaying",
      "ic_change_pct": -95.1,
      "score_mean_60d": 62.6,
      "score_std_60d": 22.1,
      "zone_distribution_60d": {
        "extreme_fear": 1,
        "fear": 10,
        "neutral": 20,
        "greed": 4,
        "extreme_greed": 22
      },
      "health": "poor",
      "flags": [
        "IC decaying: recent -0.0033 vs historical -0.0678",
        "Weak IC: -0.0033"
      ],
      "calibration_stale": false,
      "calibration_days_ago": 23
    },
    "kr": {
      "full_ic_20d": -0.1097,
      "recent_ic_20d": -0.4105,
      "ic_trend": "improving",
      "ic_change_pct": 274.2,
      "score_mean_60d": 62.0,
      "score_std_60d": 20.6,
      "zone_distribution_60d": {
        "extreme_fear": 2,
        "fear": 8,
        "neutral": 14,
        "greed": 19,
        "extreme_greed": 15
      },
      "health": "good",
      "flags": [
        "Calibration stale: 2026-04-11 (74d ago)"
      ],
      "calibration_stale": true,
      "calibration_days_ago": 74
    },
    "eu": {
      "full_ic_20d": -0.0571,
      "recent_ic_20d": -0.1462,
      "ic_trend": "improving",
      "ic_change_pct": 156.0,
      "score_mean_60d": 69.5,
      "score_std_60d": 12.7,
      "zone_distribution_60d": {
        "extreme_fear": 0,
        "fear": 2,
        "neutral": 12,
        "greed": 19,
        "extreme_greed": 24
      },
      "health": "warning",
      "flags": [
        "Calibration stale: 2026-04-11 (74d ago)"
      ],
      "calibration_stale": true,
      "calibration_days_ago": 74
    }
  },
  "system_health": {
    "overall": "poor",
    "active_flags": [
      "US: IC decaying: recent 0.3439 vs historical -0.1556",
      "TW: IC decaying: recent 0.3403 vs historical -0.1145",
      "TW: Score stuck in extreme_greed zone 94% of last 60d",
      "JP: IC decaying: recent -0.0033 vs historical -0.0678",
      "JP: Weak IC: -0.0033",
      "US: Calibration stale: 2026-03-25 (91d ago)",
      "TW: Calibration stale: 2026-04-11 (74d ago)",
      "KR: Calibration stale: 2026-04-11 (74d ago)",
      "EU: Calibration stale: 2026-04-11 (74d ago)"
    ],
    "last_calibration": "2026-06-01",
    "recommendation": "Signal degradation detected. Consider recalibration."
  }
}