{
  "date": "2026-04-20",
  "data_sources": {
    "market_prices": "Yahoo Finance (yfinance)",
    "tw_margin": "FinMind API (TWSE OpenData)",
    "tw_institutional": "FinMind API (三大法人)",
    "scoring_method": "Rolling 252-day Z-score normalization",
    "behavioral_params": "Kahneman & Tversky (1979), Banerjee (1992)"
  },
  "us_market": {
    "SPY_close": 706.55,
    "SPY_RSI14": 95.1,
    "SPY_SMA20": 669.52,
    "SPY_SMA60": 676.89,
    "SPY_vs_52w_high_pct": 99.5,
    "SPY_5d_return_pct": 2.98,
    "SPY_20d_return_pct": 8.94,
    "VIX": 19.56,
    "US_10Y_yield": 4.27
  },
  "tw_market": {
    "TAIEX_close": 36959.0,
    "TAIEX_RSI14": 72.7,
    "TAIEX_SMA20": 34320.0,
    "TAIEX_vs_52w_high_pct": 99.5,
    "TAIEX_5d_return_pct": 4.23,
    "TAIEX_20d_return_pct": 9.7,
    "TSMC_close": 2025.0,
    "TSMC_vs_52w_high_pct": 97.1
  },
  "tw_retail_indicators": {
    "margin_balance": 8562532,
    "margin_5d_change_pct": 2.1,
    "margin_5d_trend": "INCREASING",
    "institutional_net_TWD": -25.3,
    "retail_net_est_TWD": 25.3,
    "foreign_net_TWD": 43.5,
    "foreign_consecutive_days": 1,
    "foreign_consecutive_direction": "buy",
    "TSMC_margin_balance": 26012,
    "TSMC_margin_30d_change_pct": 10.07
  },
  "jp_market": {
    "NIKKEI_close": 58475.9,
    "NIKKEI_RSI14": 72.7,
    "NIKKEI_SMA20": 54662.49,
    "NIKKEI_vs_52w_high_pct": 98.2,
    "NIKKEI_5d_return_pct": 2.73,
    "NIKKEI_20d_return_pct": 9.56,
    "jp_moodring_score": 95.2
  },
  "kr_market": {
    "KOSPI_close": 6191.92,
    "KOSPI_RSI14": 70.7,
    "KOSPI_SMA20": 5633.05,
    "KOSPI_vs_52w_high_pct": 98.2,
    "KOSPI_5d_return_pct": 5.68,
    "KOSPI_20d_return_pct": 7.1,
    "kr_moodring_score": 93.2
  },
  "eu_market": {
    "STOXX50_close": 5974.62,
    "STOXX50_RSI14": 73.1,
    "STOXX50_SMA20": 5753.98,
    "STOXX50_vs_52w_high_pct": 96.8,
    "STOXX50_5d_return_pct": 1.18,
    "STOXX50_20d_return_pct": 6.43,
    "eu_moodring_score": 76.1
  },
  "global_context": {
    "Gold": 4817.0,
    "USDJPY": 158.75,
    "USDTWD": 31.42
  }
}